main/__init__.py
main/main.py
watchbot-0.0.0.dist-info/METADATA
watchbot-0.0.0.dist-info/WHEEL
watchbot-0.0.0.dist-info/top_level.txt
watchbot-0.0.0.dist-info/RECORD
